{"stats":{"minecraft:custom":{"minecraft:jump":8,"minecraft:time_since_rest":2645,"minecraft:crouch_one_cm":78,"minecraft:leave_game":3,"minecraft:play_time":2645,"minecraft:sprint_one_cm":124,"minecraft:time_since_death":2645,"minecraft:walk_one_cm":7242,"minecraft:sneak_time":10,"minecraft:traded_with_villager":16,"minecraft:total_world_time":2691,"minecraft:fly_one_cm":283,"minecraft:drop":37},"minecraft:dropped":{"minecraft:iron_boots":23,"minecraft:chainmail_boots":11,"minecraft:emerald":3},"minecraft:crafted":{"minecraft:air":0,"minecraft:emerald":4,"minecraft:iron_boots":12}},"DataVersion":2975}